neox/__init__.py
neox/attend.py
neox/model.py
neox/transformer.py
neox-0.1.3.dist-info/LICENSE
neox-0.1.3.dist-info/WHEEL
neox-0.1.3.dist-info/METADATA
neox-0.1.3.dist-info/RECORD
