Metadata-Version: 2.1
Name: neox
Version: 0.1.3
Summary: An Multi-Modality Foundation Model for Humanoid robots
Home-page: https://github.com/kyegomez/NeoCortex
License: Attribution-NonCommercial 4.0 International
Author: Kye Gomez
Author-email: kye@apac.ai
Requires-Python: >=3.6,<4.0
Classifier: License :: Other/Proprietary License
Classifier: Programming Language :: Python :: 3
Classifier: Programming Language :: Python :: 3.6
Classifier: Programming Language :: Python :: 3.7
Classifier: Programming Language :: Python :: 3.8
Classifier: Programming Language :: Python :: 3.9
Classifier: Programming Language :: Python :: 3.10
Classifier: Programming Language :: Python :: 3.11
Requires-Dist: einops
Requires-Dist: torch
Requires-Dist: transformers
Project-URL: Repository, https://github.com/kyegomez/NeoCortex
